{
 "cells": [
  {
   "cell_type": "code",
   "execution_count": 1,
   "metadata": {},
   "outputs": [],
   "source": [
    "from scipy import misc"
   ]
  },
  {
   "cell_type": "code",
   "execution_count": 7,
   "metadata": {},
   "outputs": [
    {
     "name": "stdout",
     "output_type": "stream",
     "text": [
      "Iterations = 3.386274509803922\n",
      "Iterations = 2.1940421996902124\n",
      "Iterations = 1.0213612844870927\n",
      "Iterations = -6.064715000477431\n",
      "Iterations = -3.980292142483117\n",
      "Iterations = -2.6545722507864236\n",
      "Iterations = -1.89354698949463\n",
      "Iterations = -1.5723744559981774\n",
      "Iterations = -1.5113165796472743\n",
      "Iterations = -1.509214480427019\n",
      "Iterations = -1.5092120367082593\n",
      "The value of the root is :  -1.5092\n"
     ]
    }
   ],
   "source": [
    "# Newton Raphson Method for extended example of creation IR:\n",
    "# The function is : (4/3)x^3 - (3/2)x^2 + 8\n",
    "def function( x ):\n",
    "    return 4/3*x * x * x - 3/2*x * x + 8\n",
    " \n",
    "# Derivative of the function\n",
    "def derivedFunction( x ):\n",
    "    return 4 * x * x - 3 * x\n",
    " \n",
    "# Function to find the root\n",
    "def newtonIteration( x ):\n",
    "    h = function(x) / derivedFunction(x)\n",
    "    while abs(h) >= 0.0001:\n",
    "        h = function(x)/derivedFunction(x)\n",
    "         \n",
    "        # x(i+1) = x(i) - f(x) / f'(x)\n",
    "        x = x - h\n",
    "        print(\"Iterations =\" ,x)\n",
    "    print(\"The value of the root is : \",\n",
    "                             \"%.4f\"% x)\n",
    "\n",
    "# Testing\n",
    "x0 = 5 # Initial value\n",
    "newtonIteration(x0)\n",
    "# As a results we need to find -1.5092"
   ]
  },
  {
   "cell_type": "code",
   "execution_count": 3,
   "metadata": {},
   "outputs": [],
   "source": [
    "import dis\n",
    "import ast"
   ]
  },
  {
   "cell_type": "markdown",
   "metadata": {},
   "source": [
    "for ByteCode Representation of the Code is:"
   ]
  },
  {
   "cell_type": "code",
   "execution_count": 8,
   "metadata": {},
   "outputs": [
    {
     "name": "stdout",
     "output_type": "stream",
     "text": [
      " 12           0 LOAD_GLOBAL              0 (function)\n",
      "              2 LOAD_FAST                0 (x)\n",
      "              4 CALL_FUNCTION            1\n",
      "              6 LOAD_GLOBAL              1 (derivedFunction)\n",
      "              8 LOAD_FAST                0 (x)\n",
      "             10 CALL_FUNCTION            1\n",
      "             12 BINARY_TRUE_DIVIDE\n",
      "             14 STORE_FAST               1 (h)\n",
      "\n",
      " 13     >>   16 LOAD_GLOBAL              2 (abs)\n",
      "             18 LOAD_FAST                1 (h)\n",
      "             20 CALL_FUNCTION            1\n",
      "             22 LOAD_CONST               1 (0.0001)\n",
      "             24 COMPARE_OP               5 (>=)\n",
      "             26 POP_JUMP_IF_FALSE       64\n",
      "\n",
      " 14          28 LOAD_GLOBAL              0 (function)\n",
      "             30 LOAD_FAST                0 (x)\n",
      "             32 CALL_FUNCTION            1\n",
      "             34 LOAD_GLOBAL              1 (derivedFunction)\n",
      "             36 LOAD_FAST                0 (x)\n",
      "             38 CALL_FUNCTION            1\n",
      "             40 BINARY_TRUE_DIVIDE\n",
      "             42 STORE_FAST               1 (h)\n",
      "\n",
      " 17          44 LOAD_FAST                0 (x)\n",
      "             46 LOAD_FAST                1 (h)\n",
      "             48 BINARY_SUBTRACT\n",
      "             50 STORE_FAST               0 (x)\n",
      "\n",
      " 18          52 LOAD_GLOBAL              3 (print)\n",
      "             54 LOAD_CONST               2 ('Iterations =')\n",
      "             56 LOAD_FAST                0 (x)\n",
      "             58 CALL_FUNCTION            2\n",
      "             60 POP_TOP\n",
      "             62 JUMP_ABSOLUTE           16\n",
      "\n",
      " 19     >>   64 LOAD_GLOBAL              3 (print)\n",
      "             66 LOAD_CONST               3 ('The value of the root is : ')\n",
      "\n",
      " 20          68 LOAD_CONST               4 ('%.4f')\n",
      "             70 LOAD_FAST                0 (x)\n",
      "             72 BINARY_MODULO\n",
      "\n",
      " 19          74 CALL_FUNCTION            2\n",
      "             76 POP_TOP\n",
      "             78 LOAD_CONST               0 (None)\n",
      "             80 RETURN_VALUE\n"
     ]
    }
   ],
   "source": [
    "dis.dis(newtonIteration)"
   ]
  },
  {
   "cell_type": "markdown",
   "metadata": {},
   "source": [
    "for AST representation of the CODE:"
   ]
  },
  {
   "cell_type": "code",
   "execution_count": 9,
   "metadata": {},
   "outputs": [
    {
     "name": "stdout",
     "output_type": "stream",
     "text": [
      "Module(\n",
      "    body=[\n",
      "        FunctionDef(\n",
      "            name='function',\n",
      "            args=arguments(\n",
      "                posonlyargs=[],\n",
      "                args=[\n",
      "                    arg(arg='x')],\n",
      "                kwonlyargs=[],\n",
      "                kw_defaults=[],\n",
      "                defaults=[]),\n",
      "            body=[\n",
      "                Return(\n",
      "                    value=BinOp(\n",
      "                        left=BinOp(\n",
      "                            left=BinOp(\n",
      "                                left=BinOp(\n",
      "                                    left=BinOp(\n",
      "                                        left=BinOp(\n",
      "                                            left=Constant(value=4),\n",
      "                                            op=Div(),\n",
      "                                            right=Constant(value=3)),\n",
      "                                        op=Mult(),\n",
      "                                        right=Name(id='x', ctx=Load())),\n",
      "                                    op=Mult(),\n",
      "                                    right=Name(id='x', ctx=Load())),\n",
      "                                op=Mult(),\n",
      "                                right=Name(id='x', ctx=Load())),\n",
      "                            op=Sub(),\n",
      "                            right=BinOp(\n",
      "                                left=BinOp(\n",
      "                                    left=BinOp(\n",
      "                                        left=Constant(value=3),\n",
      "                                        op=Div(),\n",
      "                                        right=Constant(value=2)),\n",
      "                                    op=Mult(),\n",
      "                                    right=Name(id='x', ctx=Load())),\n",
      "                                op=Mult(),\n",
      "                                right=Name(id='x', ctx=Load()))),\n",
      "                        op=Add(),\n",
      "                        right=Constant(value=8)))],\n",
      "            decorator_list=[]),\n",
      "        FunctionDef(\n",
      "            name='deriveFunction',\n",
      "            args=arguments(\n",
      "                posonlyargs=[],\n",
      "                args=[\n",
      "                    arg(arg='x')],\n",
      "                kwonlyargs=[],\n",
      "                kw_defaults=[],\n",
      "                defaults=[]),\n",
      "            body=[\n",
      "                Return(\n",
      "                    value=BinOp(\n",
      "                        left=BinOp(\n",
      "                            left=BinOp(\n",
      "                                left=Constant(value=4),\n",
      "                                op=Mult(),\n",
      "                                right=Name(id='x', ctx=Load())),\n",
      "                            op=Mult(),\n",
      "                            right=Name(id='x', ctx=Load())),\n",
      "                        op=Sub(),\n",
      "                        right=BinOp(\n",
      "                            left=Constant(value=3),\n",
      "                            op=Mult(),\n",
      "                            right=Name(id='x', ctx=Load()))))],\n",
      "            decorator_list=[]),\n",
      "        FunctionDef(\n",
      "            name='newtonIteration',\n",
      "            args=arguments(\n",
      "                posonlyargs=[],\n",
      "                args=[\n",
      "                    arg(arg='x')],\n",
      "                kwonlyargs=[],\n",
      "                kw_defaults=[],\n",
      "                defaults=[]),\n",
      "            body=[\n",
      "                Assign(\n",
      "                    targets=[\n",
      "                        Name(id='h', ctx=Store())],\n",
      "                    value=BinOp(\n",
      "                        left=Call(\n",
      "                            func=Name(id='function', ctx=Load()),\n",
      "                            args=[\n",
      "                                Name(id='x', ctx=Load())],\n",
      "                            keywords=[]),\n",
      "                        op=Div(),\n",
      "                        right=Call(\n",
      "                            func=Name(id='deriveFunction', ctx=Load()),\n",
      "                            args=[\n",
      "                                Name(id='x', ctx=Load())],\n",
      "                            keywords=[]))),\n",
      "                While(\n",
      "                    test=Compare(\n",
      "                        left=Call(\n",
      "                            func=Name(id='abs', ctx=Load()),\n",
      "                            args=[\n",
      "                                Name(id='h', ctx=Load())],\n",
      "                            keywords=[]),\n",
      "                        ops=[\n",
      "                            GtE()],\n",
      "                        comparators=[\n",
      "                            Constant(value=0.0001)]),\n",
      "                    body=[\n",
      "                        Assign(\n",
      "                            targets=[\n",
      "                                Name(id='h', ctx=Store())],\n",
      "                            value=BinOp(\n",
      "                                left=Call(\n",
      "                                    func=Name(id='function', ctx=Load()),\n",
      "                                    args=[\n",
      "                                        Name(id='x', ctx=Load())],\n",
      "                                    keywords=[]),\n",
      "                                op=Div(),\n",
      "                                right=Call(\n",
      "                                    func=Name(id='deriveFunction', ctx=Load()),\n",
      "                                    args=[\n",
      "                                        Name(id='x', ctx=Load())],\n",
      "                                    keywords=[]))),\n",
      "                        Assign(\n",
      "                            targets=[\n",
      "                                Name(id='x', ctx=Store())],\n",
      "                            value=BinOp(\n",
      "                                left=Name(id='x', ctx=Load()),\n",
      "                                op=Sub(),\n",
      "                                right=Name(id='h', ctx=Load()))),\n",
      "                        Expr(\n",
      "                            value=Call(\n",
      "                                func=Name(id='print', ctx=Load()),\n",
      "                                args=[\n",
      "                                    Constant(value='Iterations ='),\n",
      "                                    Name(id='x', ctx=Load())],\n",
      "                                keywords=[]))],\n",
      "                    orelse=[]),\n",
      "                Expr(\n",
      "                    value=Call(\n",
      "                        func=Name(id='print', ctx=Load()),\n",
      "                        args=[\n",
      "                            Constant(value='The value of the root is : '),\n",
      "                            BinOp(\n",
      "                                left=Constant(value='%.4f'),\n",
      "                                op=Mod(),\n",
      "                                right=Name(id='x', ctx=Load()))],\n",
      "                        keywords=[]))],\n",
      "            decorator_list=[]),\n",
      "        Assign(\n",
      "            targets=[\n",
      "                Name(id='x0', ctx=Store())],\n",
      "            value=Constant(value=5)),\n",
      "        Expr(\n",
      "            value=Call(\n",
      "                func=Name(id='newtonIteration', ctx=Load()),\n",
      "                args=[\n",
      "                    Name(id='x0', ctx=Load())],\n",
      "                keywords=[]))],\n",
      "    type_ignores=[])\n"
     ]
    }
   ],
   "source": [
    "print(ast.dump(ast.parse(\"\"\"\n",
    "# Newton Raphson Method for extended example of creation IR:\n",
    "# The function is : (4/3)x^3 - (3/2)x^2 + 8\n",
    "def function( x ):\n",
    "    return 4/3*x * x * x - 3/2*x * x + 8\n",
    " \n",
    "# Derivative of the function\n",
    "def deriveFunction( x ):\n",
    "    return 4 * x * x - 3 * x\n",
    " \n",
    "# Function to find the root\n",
    "def newtonIteration( x ):\n",
    "    h = function(x) / deriveFunction(x)\n",
    "    while abs(h) >= 0.0001:\n",
    "        h = function(x)/deriveFunction(x)\n",
    "         \n",
    "        # x(i+1) = x(i) - f(x) / f'(x)\n",
    "        x = x - h\n",
    "        print(\"Iterations =\" ,x)\n",
    "    print(\"The value of the root is : \",\n",
    "                             \"%.4f\"% x)\n",
    "\n",
    "# Testing\n",
    "x0 = 5 # Initial value\n",
    "newtonIteration(x0)\n",
    "# As a results we need to find -1.5092\n",
    "\"\"\"), indent=4))"
   ]
  },
  {
   "cell_type": "markdown",
   "metadata": {},
   "source": [
    "NUMBA IR version will be added."
   ]
  }
 ],
 "metadata": {
  "interpreter": {
   "hash": "c6e4e9f98eb68ad3b7c296f83d20e6de614cb42e90992a65aa266555a3137d0d"
  },
  "kernelspec": {
   "display_name": "Python 3.9.10 ('base')",
   "language": "python",
   "name": "python3"
  },
  "language_info": {
   "codemirror_mode": {
    "name": "ipython",
    "version": 3
   },
   "file_extension": ".py",
   "mimetype": "text/x-python",
   "name": "python",
   "nbconvert_exporter": "python",
   "pygments_lexer": "ipython3",
   "version": "3.9.10"
  },
  "orig_nbformat": 4
 },
 "nbformat": 4,
 "nbformat_minor": 2
}
